osrsmath/__init__.py
osrsmath/config.py
osrsmath/apps/__init__.py
osrsmath/apps/GUI/__init__.py
osrsmath/apps/GUI/config.py
osrsmath/apps/GUI/resources.py
osrsmath/apps/GUI/monsters/__init__.py
osrsmath/apps/GUI/monsters/create_player_stat.py
osrsmath/apps/GUI/monsters/monsters_skeleton.py
osrsmath/apps/GUI/monsters/player_stats.py
osrsmath/apps/GUI/optimize/__init__.py
osrsmath/apps/GUI/optimize/ignore_adjust_skeleton.py
osrsmath/apps/GUI/optimize/optimize_skeleton.py
osrsmath/apps/GUI/optimize/player_skeleton.py
osrsmath/apps/GUI/shared/__init__.py
osrsmath/apps/GUI/shared/application.py
osrsmath/apps/GUI/shared/util.py
osrsmath/apps/GUI/shared/widgets.py
osrsmath/apps/GUI/shared/stylesheets/AMOLED.qss
osrsmath/apps/GUI/shared/stylesheets/Aqua.qss
osrsmath/apps/GUI/shared/stylesheets/ConsoleStyle.qss
osrsmath/apps/GUI/shared/stylesheets/ElegantDark.qss
osrsmath/apps/GUI/shared/stylesheets/LICENSE1
osrsmath/apps/GUI/shared/stylesheets/LICENSE2 (darkorange)
osrsmath/apps/GUI/shared/stylesheets/License.txt
osrsmath/apps/GUI/shared/stylesheets/ManjaroMix.qss
osrsmath/apps/GUI/shared/stylesheets/MaterialDark.qss
osrsmath/apps/GUI/shared/stylesheets/README.md
osrsmath/apps/GUI/shared/stylesheets/Ubuntu.qss
osrsmath/apps/GUI/shared/stylesheets/blue.css
osrsmath/apps/GUI/shared/stylesheets/darkorange.css
osrsmath/apps/GUI/shared/stylesheets/darkred.css
osrsmath/apps/monsters/__init__.py
osrsmath/apps/monsters/gui_single.py
osrsmath/apps/monsters/main.py
osrsmath/apps/monsters/panel.py
osrsmath/apps/optimize/__init__.py
osrsmath/apps/optimize/gui_single.py
osrsmath/apps/optimize/main.py
osrsmath/apps/optimize/Applications/__init__.py
osrsmath/apps/optimize/Applications/package.py
osrsmath/apps/optimize/data/ignore.json
osrsmath/apps/optimize/data/monsters.json
osrsmath/apps/optimize/data/player.json
osrsmath/apps/optimize/logic/__init__.py
osrsmath/apps/optimize/logic/evaluation.py
osrsmath/apps/optimize/logic/gear.py
osrsmath/apps/optimize/logic/optimize.py
osrsmath-0.0.3.3.dist-info/LICENSE
osrsmath-0.0.3.3.dist-info/METADATA
osrsmath-0.0.3.3.dist-info/WHEEL
osrsmath-0.0.3.3.dist-info/top_level.txt
osrsmath-0.0.3.3.dist-info/RECORD
