Metadata-Version: 2.1
Name: osrsmath
Version: 0.0.3.3
Summary: Mathematical Functions & Optimization Calculations for OSRS
Home-page: https://github.com/Palfore/OSRS-Combat/
Author: Nawar Ismail
Author-email: nawar@palfore.com
License: MIT
Keywords: math optimization old school runescape
Platform: UNKNOWN
Classifier: Development Status :: 2 - Pre-Alpha
Classifier: Intended Audience :: Developers
Classifier: License :: OSI Approved :: MIT License
Classifier: Natural Language :: English
Classifier: Topic :: Scientific/Engineering :: Mathematics
Classifier: Programming Language :: Python
Classifier: Programming Language :: Python :: 3.6
Classifier: Programming Language :: Python :: 3.7
Classifier: Programming Language :: Python :: 3.8
Requires-Python: >=3
Requires-Dist: wheel
Requires-Dist: PySide2
Requires-Dist: numpy
Requires-Dist: matplotlib
Requires-Dist: scipy
Requires-Dist: Dijkstar
Requires-Dist: requests
Requires-Dist: tornado
Requires-Dist: multiprocess
Requires-Dist: jsoncomment
